{
  "1": {
    "dqWorst": 0.3058,
    "dqAvg": 0.0368,
    "cqDelayAvg": 0.0833,
    "dSetup3SigmaAvg": 0.0346,
    "dHoldSohmAvg": 0.0602,
    "area": 114.7379,
    "ckCap": 5.8854,
    "pLeakage": 0.463,
    "pDyn": 5.2365,
    "pdpAvg": 0.0365
  },
  "2": {
    "eeckWorst": 0.1828,
    "eeckAvg": 0.2016,
    "cqDelayAvg": 0.0261,
    "eSetup3SigmaAvg": 0.0378,
    "eHoldSohmAvg": 0.0602,
    "delayTranRfRatio": 1.236,
    "area": 50.8617,
    "ckCap": 4.1588,
    "pLeakage": 3.8948,
    "pDyn": 0.376,
    "pdpAvg": 0.7272
  },
  "3": {
    "dqWorst": 0.3293,
    "dqAvg": 0.1219,
    "cqDelayAvg": 0.0558,
    "dSetup3SigmaAvg": 0.1153,
    "dHoldSohmAvg": 0.0302,
    "area": 32.9844,
    "ckCap": 1.3513,
    "pLeakage": 4.0756,
    "pDyn": 7.3636,
    "pdpAvg": 0.7283
  },
  "4": {
    "eeckWorst": 0.423,
    "eeckAvg": 0.2109,
    "cqDelayAvg": 0.2438,
    "eSetup3SigmaAvg": 0.063,
    "eHoldSohmAvg": 0.0519,
    "delayTranRfRatio": 1.4635,
    "area": 106.5928,
    "ckCap": 5.7117,
    "pLeakage": 2.7924,
    "pDyn": 8.5435,
    "pdpAvg": 0.0508
  },
  "5": {
    "dqWorst": 0.1412,
    "dqAvg": 0.1081,
    "cqDelayAvg": 0.0384,
    "dSetup3SigmaAvg": 0.0356,
    "dHoldSohmAvg": 0.0126,
    "area": 58.9163,
    "ckCap": 4.4234,
    "pLeakage": 1.783,
    "pDyn": 4.6311,
    "pdpAvg": 0.1965
  },
  "6": {
    "eeckWorst": 0.2055,
    "eeckAvg": 0.331,
    "cqDelayAvg": 0.169,
    "eSetup3SigmaAvg": 0.0953,
    "eHoldSohmAvg": 0.0195,
    "delayTranRfRatio": 1.3833,
    "area": 42.8763,
    "ckCap": 2.9629,
    "pLeakage": 4.7502,
    "pDyn": 7.788,
    "pdpAvg": 0.5057
  },
  "7": {
    "dqWorst": 0.3238,
    "dqAvg": 0.2576,
    "cqDelayAvg": 0.1985,
    "dSetup3SigmaAvg": 0.0352,
    "dHoldSohmAvg": 0.0074,
    "area": 64.1634,
    "ckCap": 2.3261,
    "pLeakage": 1.0522,
    "pDyn": 11.332,
    "pdpAvg": 0.79
  },
  "8": {
    "eeckWorst": 0.2279,
    "eeckAvg": 0.2466,
    "cqDelayAvg": 0.111,
    "eSetup3SigmaAvg": 0.138,
    "eHoldSohmAvg": 0.044,
    "delayTranRfRatio": 1.0119,
    "area": 54.5279,
    "ckCap": 3.9998,
    "pLeakage": 1.298,
    "pDyn": 7.1397,
    "pdpAvg": 0.8091
  },
  "9": {
    "dqWorst": 0.2098,
    "dqAvg": 0.0892,
    "cqDelayAvg": 0.2494,
    "dSetup3SigmaAvg": 0.066,
    "dHoldSohmAvg": 0.0118,
    "area": 26.5963,
    "ckCap": 1.425,
    "pLeakage": 3.0304,
    "pDyn": 9.5673,
    "pdpAvg": 0.3857
  },
  "10": {
    "eeckWorst": 0.1099,
    "eeckAvg": 0.1645,
    "cqDelayAvg": 0.2491,
    "eSetup3SigmaAvg": 0.0841,
    "eHoldSohmAvg": 0.0875,
    "delayTranRfRatio": 1.4886,
    "area": 21.6073,
    "ckCap": 4.9081,
    "pLeakage": 3.2881,
    "pDyn": 6.5826,
    "pdpAvg": 0.2475
  },
  "11": {
    "dqWorst": 0.3064,
    "dqAvg": 0.0601,
    "cqDelayAvg": 0.12,
    "dSetup3SigmaAvg": 0.0599,
    "dHoldSohmAvg": 0.0765,
    "area": 142.6194,
    "ckCap": 2.3013,
    "pLeakage": 2.4278,
    "pDyn": 2.3902,
    "pdpAvg": 0.8222
  },
  "12": {
    "eeckWorst": 0.4891,
    "eeckAvg": 0.1395,
    "cqDelayAvg": 0.167,
    "eSetup3SigmaAvg": 0.0953,
    "eHoldSohmAvg": 0.018,
    "delayTranRfRatio": 1.41,
    "area": 95.5131,
    "ckCap": 5.2382,
    "pLeakage": 2.5692,
    "pDyn": 0.3067,
    "pdpAvg": 0.2985
  },
  "13": {
    "dqWorst": 0.0578,
    "dqAvg": 0.2809,
    "cqDelayAvg": 0.2221,
    "dSetup3SigmaAvg": 0.1015,
    "dHoldSohmAvg": 0.0281,
    "area": 28.1095,
    "ckCap": 5.8047,
    "pLeakage": 4.548,
    "pDyn": 1.3021,
    "pdpAvg": 0.4425
  },
  "14": {
    "eeckWorst": 0.1125,
    "eeckAvg": 0.2782,
    "cqDelayAvg": 0.1961,
    "eSetup3SigmaAvg": 0.028,
    "eHoldSohmAvg": 0.0454,
    "delayTranRfRatio": 1.2398,
    "area": 57.1079,
    "ckCap": 5.7729,
    "pLeakage": 2.0599,
    "pDyn": 2.778,
    "pdpAvg": 0.49
  },
  "15": {
    "dqWorst": 0.342,
    "dqAvg": 0.0843,
    "cqDelayAvg": 0.0917,
    "dSetup3SigmaAvg": 0.1195,
    "dHoldSohmAvg": 0.0537,
    "area": 81.334,
    "ckCap": 3.7502,
    "pLeakage": 0.6248,
    "pDyn": 2.929,
    "pdpAvg": 0.3109
  },
  "16": {
    "eeckWorst": 0.3565,
    "eeckAvg": 0.119,
    "cqDelayAvg": 0.0706,
    "eSetup3SigmaAvg": 0.0199,
    "eHoldSohmAvg": 0.0586,
    "delayTranRfRatio": 0.9832,
    "area": 146.7588,
    "ckCap": 5.6999,
    "pLeakage": 0.3866,
    "pDyn": 3.0847,
    "pdpAvg": 0.6054
  },
  "17": {
    "dqWorst": 0.1357,
    "dqAvg": 0.0657,
    "cqDelayAvg": 0.2352,
    "dSetup3SigmaAvg": 0.0728,
    "dHoldSohmAvg": 0.0405,
    "area": 129.8467,
    "ckCap": 5.4027,
    "pLeakage": 0.9544,
    "pDyn": 1.4341,
    "pdpAvg": 0.3936
  },
  "18": {
    "eeckWorst": 0.2791,
    "eeckAvg": 0.1901,
    "cqDelayAvg": 0.1877,
    "eSetup3SigmaAvg": 0.1043,
    "eHoldSohmAvg": 0.0887,
    "delayTranRfRatio": 0.8787,
    "area": 76.367,
    "ckCap": 2.734,
    "pLeakage": 4.1429,
    "pDyn": 3.2093,
    "pdpAvg": 0.1793
  },
  "19": {
    "dqWorst": 0.2294,
    "dqAvg": 0.1439,
    "cqDelayAvg": 0.0841,
    "dSetup3SigmaAvg": 0.0375,
    "dHoldSohmAvg": 0.0742,
    "area": 82.0383,
    "ckCap": 5.7097,
    "pLeakage": 2.664,
    "pDyn": 0.8919,
    "pdpAvg": 0.8994
  },
  "20": {
    "eeckWorst": 0.4729,
    "eeckAvg": 0.3407,
    "cqDelayAvg": 0.2331,
    "eSetup3SigmaAvg": 0.1288,
    "eHoldSohmAvg": 0.0191,
    "delayTranRfRatio": 1.1885,
    "area": 49.9246,
    "ckCap": 3.0859,
    "pLeakage": 0.3285,
    "pDyn": 4.734,
    "pdpAvg": 0.8869
  },
  "21": {
    "dqWorst": 0.1561,
    "dqAvg": 0.2417,
    "cqDelayAvg": 0.1247,
    "dSetup3SigmaAvg": 0.0565,
    "dHoldSohmAvg": 0.0768,
    "area": 159.3592,
    "ckCap": 3.9679,
    "pLeakage": 3.4624,
    "pDyn": 2.1111,
    "pdpAvg": 0.2741
  },
  "22": {
    "eeckWorst": 0.5353,
    "eeckAvg": 0.2238,
    "cqDelayAvg": 0.1447,
    "eSetup3SigmaAvg": 0.1147,
    "eHoldSohmAvg": 0.0099,
    "delayTranRfRatio": 1.2673,
    "area": 90.3991,
    "ckCap": 5.6605,
    "pLeakage": 0.7978,
    "pDyn": 11.5411,
    "pdpAvg": 0.0813
  },
  "23": {
    "dqWorst": 0.1243,
    "dqAvg": 0.1907,
    "cqDelayAvg": 0.1753,
    "dSetup3SigmaAvg": 0.0359,
    "dHoldSohmAvg": 0.014,
    "area": 144.6402,
    "ckCap": 2.2034,
    "pLeakage": 2.874,
    "pDyn": 7.5468,
    "pdpAvg": 0.3831
  },
  "24": {
    "eeckWorst": 0.3543,
    "eeckAvg": 0.2068,
    "cqDelayAvg": 0.235,
    "eSetup3SigmaAvg": 0.0386,
    "eHoldSohmAvg": 0.0659,
    "delayTranRfRatio": 0.9909,
    "area": 75.41,
    "ckCap": 4.6286,
    "pLeakage": 1.475,
    "pDyn": 3.9993,
    "pdpAvg": 0.6792
  },
  "25": {
    "dqWorst": 0.079,
    "dqAvg": 0.1537,
    "cqDelayAvg": 0.2496,
    "dSetup3SigmaAvg": 0.1196,
    "dHoldSohmAvg": 0.0105,
    "area": 49.8416,
    "ckCap": 2.3116,
    "pLeakage": 4.483,
    "pDyn": 10.6061,
    "pdpAvg": 0.7926
  },
  "26": {
    "eeckWorst": 0.2537,
    "eeckAvg": 0.0973,
    "cqDelayAvg": 0.2118,
    "eSetup3SigmaAvg": 0.1085,
    "eHoldSohmAvg": 0.057,
    "delayTranRfRatio": 1.5898,
    "area": 111.5567,
    "ckCap": 0.8446,
    "pLeakage": 3.9312,
    "pDyn": 3.8027,
    "pdpAvg": 0.6004
  },
  "27": {
    "dqWorst": 0.4256,
    "dqAvg": 0.0663,
    "cqDelayAvg": 0.0465,
    "dSetup3SigmaAvg": 0.0218,
    "dHoldSohmAvg": 0.0465,
    "area": 58.1287,
    "ckCap": 4.2475,
    "pLeakage": 3.4587,
    "pDyn": 2.6821,
    "pdpAvg": 0.5745
  },
  "28": {
    "eeckWorst": 0.2041,
    "eeckAvg": 0.1966,
    "cqDelayAvg": 0.2282,
    "eSetup3SigmaAvg": 0.1285,
    "eHoldSohmAvg": 0.0128,
    "delayTranRfRatio": 1.1389,
    "area": 58.7352,
    "ckCap": 0.8202,
    "pLeakage": 3.7128,
    "pDyn": 7.7542,
    "pdpAvg": 0.2431
  },
  "29": {
    "dqWorst": 0.3465,
    "dqAvg": 0.179,
    "cqDelayAvg": 0.1184,
    "dSetup3SigmaAvg": 0.0111,
    "dHoldSohmAvg": 0.0106,
    "area": 143.6349,
    "ckCap": 5.9524,
    "pLeakage": 2.6416,
    "pDyn": 10.0648,
    "pdpAvg": 0.5284
  },
  "30": {
    "eeckWorst": 0.1496,
    "eeckAvg": 0.0882,
    "cqDelayAvg": 0.0909,
    "eSetup3SigmaAvg": 0.1359,
    "eHoldSohmAvg": 0.0727,
    "delayTranRfRatio": 1.4886,
    "area": 145.8494,
    "ckCap": 1.9974,
    "pLeakage": 1.2353,
    "pDyn": 1.5027,
    "pdpAvg": 0.7043
  },
  "31": {
    "dqWorst": 0.4037,
    "dqAvg": 0.1397,
    "cqDelayAvg": 0.1628,
    "dSetup3SigmaAvg": 0.027,
    "dHoldSohmAvg": 0.0747,
    "area": 141.0448,
    "ckCap": 6.3644,
    "pLeakage": 3.9012,
    "pDyn": 10.6126,
    "pdpAvg": 0.0321
  },
  "32": {
    "eeckWorst": 0.4262,
    "eeckAvg": 0.1497,
    "cqDelayAvg": 0.2341,
    "eSetup3SigmaAvg": 0.1223,
    "eHoldSohmAvg": 0.0784,
    "delayTranRfRatio": 1.4486,
    "area": 57.3528,
    "ckCap": 5.288,
    "pLeakage": 0.5635,
    "pDyn": 10.5044,
    "pdpAvg": 0.7741
  },
  "33": {
    "dqWorst": 0.139,
    "dqAvg": 0.2505,
    "cqDelayAvg": 0.1259,
    "dSetup3SigmaAvg": 0.0436,
    "dHoldSohmAvg": 0.0647,
    "area": 51.8634,
    "ckCap": 0.9349,
    "pLeakage": 0.9674,
    "pDyn": 4.1407,
    "pdpAvg": 0.7793
  },
  "34": {
    "eeckWorst": 0.5344,
    "eeckAvg": 0.1337,
    "cqDelayAvg": 0.1675,
    "eSetup3SigmaAvg": 0.066,
    "eHoldSohmAvg": 0.0884,
    "delayTranRfRatio": 1.229,
    "area": 151.4932,
    "ckCap": 1.4574,
    "pLeakage": 4.6594,
    "pDyn": 2.3892,
    "pdpAvg": 0.8667
  },
  "35": {
    "dqWorst": 0.1562,
    "dqAvg": 0.0593,
    "cqDelayAvg": 0.1199,
    "dSetup3SigmaAvg": 0.0901,
    "dHoldSohmAvg": 0.0285,
    "area": 104.8692,
    "ckCap": 3.7151,
    "pLeakage": 1.8797,
    "pDyn": 7.0461,
    "pdpAvg": 0.2367
  },
  "36": {
    "eeckWorst": 0.4131,
    "eeckAvg": 0.0505,
    "cqDelayAvg": 0.2329,
    "eSetup3SigmaAvg": 0.0854,
    "eHoldSohmAvg": 0.0662,
    "delayTranRfRatio": 1.3936,
    "area": 113.888,
    "ckCap": 2.8761,
    "pLeakage": 0.3824,
    "pDyn": 8.0716,
    "pdpAvg": 0.3039
  },
  "37": {
    "dqWorst": 0.1756,
    "dqAvg": 0.259,
    "cqDelayAvg": 0.1855,
    "dSetup3SigmaAvg": 0.043,
    "dHoldSohmAvg": 0.0282,
    "area": 77.175,
    "ckCap": 3.0937,
    "pLeakage": 1.4544,
    "pDyn": 1.7893,
    "pdpAvg": 0.3842
  },
  "38": {
    "eeckWorst": 0.522,
    "eeckAvg": 0.2532,
    "cqDelayAvg": 0.2276,
    "eSetup3SigmaAvg": 0.0962,
    "eHoldSohmAvg": 0.0306,
    "delayTranRfRatio": 1.2383,
    "area": 20.0568,
    "ckCap": 2.4354,
    "pLeakage": 2.092,
    "pDyn": 7.0858,
    "pdpAvg": 0.5927
  },
  "39": {
    "dqWorst": 0.236,
    "dqAvg": 0.1494,
    "cqDelayAvg": 0.0692,
    "dSetup3SigmaAvg": 0.0621,
    "dHoldSohmAvg": 0.0726,
    "area": 131.4435,
    "ckCap": 1.7672,
    "pLeakage": 0.4528,
    "pDyn": 6.3308,
    "pdpAvg": 0.5733
  },
  "40": {
    "eeckWorst": 0.2375,
    "eeckAvg": 0.2955,
    "cqDelayAvg": 0.1928,
    "eSetup3SigmaAvg": 0.1042,
    "eHoldSohmAvg": 0.0241,
    "delayTranRfRatio": 0.9593,
    "area": 23.4196,
    "ckCap": 2.1956,
    "pLeakage": 2.3069,
    "pDyn": 10.2419,
    "pdpAvg": 0.0748
  },
  "41": {
    "dqWorst": 0.2158,
    "dqAvg": 0.2,
    "cqDelayAvg": 0.0647,
    "dSetup3SigmaAvg": 0.0866,
    "dHoldSohmAvg": 0.0421,
    "area": 54.1578,
    "ckCap": 4.5395,
    "pLeakage": 0.0763,
    "pDyn": 9.0863,
    "pdpAvg": 0.6953
  },
  "42": {
    "eeckWorst": 0.1301,
    "eeckAvg": 0.1775,
    "cqDelayAvg": 0.0605,
    "eSetup3SigmaAvg": 0.1441,
    "eHoldSohmAvg": 0.049,
    "delayTranRfRatio": 0.8402,
    "area": 54.8878,
    "ckCap": 5.6355,
    "pLeakage": 2.2182,
    "pDyn": 9.6766,
    "pdpAvg": 0.6041
  },
  "43": {
    "dqWorst": 0.4452,
    "dqAvg": 0.1908,
    "cqDelayAvg": 0.2385,
    "dSetup3SigmaAvg": 0.1081,
    "dHoldSohmAvg": 0.0509,
    "area": 120.6984,
    "ckCap": 3.6772,
    "pLeakage": 3.9952,
    "pDyn": 6.7101,
    "pdpAvg": 0.8085
  },
  "44": {
    "eeckWorst": 0.4295,
    "eeckAvg": 0.1924,
    "cqDelayAvg": 0.0796,
    "eSetup3SigmaAvg": 0.0446,
    "eHoldSohmAvg": 0.0592,
    "delayTranRfRatio": 1.4127,
    "area": 92.982,
    "ckCap": 4.3725,
    "pLeakage": 1.3543,
    "pDyn": 1.2066,
    "pdpAvg": 0.2643
  },
  "45": {
    "dqWorst": 0.1587,
    "dqAvg": 0.1163,
    "cqDelayAvg": 0.1442,
    "dSetup3SigmaAvg": 0.0252,
    "dHoldSohmAvg": 0.0223,
    "area": 117.153,
    "ckCap": 4.8266,
    "pLeakage": 0.3551,
    "pDyn": 5.0689,
    "pdpAvg": 0.4929
  },
  "46": {
    "eeckWorst": 0.2754,
    "eeckAvg": 0.1121,
    "cqDelayAvg": 0.1166,
    "eSetup3SigmaAvg": 0.1367,
    "eHoldSohmAvg": 0.0546,
    "delayTranRfRatio": 1.3564,
    "area": 139.9425,
    "ckCap": 5.1639,
    "pLeakage": 1.8568,
    "pDyn": 0.369,
    "pdpAvg": 0.3231
  },
  "47": {
    "dqWorst": 0.3514,
    "dqAvg": 0.2604,
    "cqDelayAvg": 0.2393,
    "dSetup3SigmaAvg": 0.0561,
    "dHoldSohmAvg": 0.0611,
    "area": 96.4585,
    "ckCap": 4.2385,
    "pLeakage": 1.0976,
    "pDyn": 2.8672,
    "pdpAvg": 0.3979
  },
  "48": {
    "eeckWorst": 0.0936,
    "eeckAvg": 0.1508,
    "cqDelayAvg": 0.1762,
    "eSetup3SigmaAvg": 0.0666,
    "eHoldSohmAvg": 0.019,
    "delayTranRfRatio": 1.1739,
    "area": 37.8679,
    "ckCap": 4.3469,
    "pLeakage": 0.1781,
    "pDyn": 4.91,
    "pdpAvg": 0.5123
  },
  "49": {
    "dqWorst": 0.0608,
    "dqAvg": 0.2035,
    "cqDelayAvg": 0.0512,
    "dSetup3SigmaAvg": 0.0608,
    "dHoldSohmAvg": 0.0088,
    "area": 73.0745,
    "ckCap": 2.0065,
    "pLeakage": 1.6025,
    "pDyn": 9.2064,
    "pdpAvg": 0.3474
  },
  "50": {
    "eeckWorst": 0.4334,
    "eeckAvg": 0.2996,
    "cqDelayAvg": 0.078,
    "eSetup3SigmaAvg": 0.0215,
    "eHoldSohmAvg": 0.0066,
    "delayTranRfRatio": 1.2315,
    "area": 159.9871,
    "ckCap": 2.7948,
    "pLeakage": 3.1382,
    "pDyn": 9.4404,
    "pdpAvg": 0.5901
  },
  "51": {
    "dqWorst": 0.3517,
    "dqAvg": 0.2864,
    "cqDelayAvg": 0.0659,
    "dSetup3SigmaAvg": 0.0122,
    "dHoldSohmAvg": 0.0164,
    "area": 37.6709,
    "ckCap": 4.6159,
    "pLeakage": 2.7289,
    "pDyn": 2.8502,
    "pdpAvg": 0.6325
  },
  "52": {
    "eeckWorst": 0.4404,
    "eeckAvg": 0.1003,
    "cqDelayAvg": 0.1597,
    "eSetup3SigmaAvg": 0.1147,
    "eHoldSohmAvg": 0.0147,
    "delayTranRfRatio": 1.4554,
    "area": 155.0609,
    "ckCap": 1.4162,
    "pLeakage": 0.172,
    "pDyn": 3.9499,
    "pdpAvg": 0.6128
  },
  "53": {
    "dqWorst": 0.4333,
    "dqAvg": 0.1371,
    "cqDelayAvg": 0.1845,
    "dSetup3SigmaAvg": 0.0184,
    "dHoldSohmAvg": 0.0568,
    "area": 107.8139,
    "ckCap": 1.3808,
    "pLeakage": 3.7193,
    "pDyn": 10.2484,
    "pdpAvg": 0.5444
  },
  "54": {
    "eeckWorst": 0.1369,
    "eeckAvg": 0.3452,
    "cqDelayAvg": 0.2,
    "eSetup3SigmaAvg": 0.0586,
    "eHoldSohmAvg": 0.0414,
    "delayTranRfRatio": 1.0965,
    "area": 90.8345,
    "ckCap": 2.745,
    "pLeakage": 4.0855,
    "pDyn": 9.9213,
    "pdpAvg": 0.1039
  },
  "55": {
    "dqWorst": 0.4343,
    "dqAvg": 0.2016,
    "cqDelayAvg": 0.2106,
    "dSetup3SigmaAvg": 0.0878,
    "dHoldSohmAvg": 0.0377,
    "area": 122.7313,
    "ckCap": 6.3032,
    "pLeakage": 1.3329,
    "pDyn": 9.7559,
    "pdpAvg": 0.489
  },
  "56": {
    "eeckWorst": 0.3072,
    "eeckAvg": 0.1807,
    "cqDelayAvg": 0.1881,
    "eSetup3SigmaAvg": 0.0476,
    "eHoldSohmAvg": 0.0774,
    "delayTranRfRatio": 1.4646,
    "area": 32.1328,
    "ckCap": 5.8253,
    "pLeakage": 1.2084,
    "pDyn": 5.7371,
    "pdpAvg": 0.5532
  },
  "57": {
    "dqWorst": 0.2016,
    "dqAvg": 0.0377,
    "cqDelayAvg": 0.2157,
    "dSetup3SigmaAvg": 0.03,
    "dHoldSohmAvg": 0.0209,
    "area": 131.6965,
    "ckCap": 2.7399,
    "pLeakage": 4.2315,
    "pDyn": 8.5038,
    "pdpAvg": 0.2559
  },
  "58": {
    "eeckWorst": 0.0848,
    "eeckAvg": 0.3344,
    "cqDelayAvg": 0.0397,
    "eSetup3SigmaAvg": 0.1108,
    "eHoldSohmAvg": 0.0465,
    "delayTranRfRatio": 1.4065,
    "area": 116.6853,
    "ckCap": 4.4816,
    "pLeakage": 2.3814,
    "pDyn": 9.5773,
    "pdpAvg": 0.0928
  },
  "59": {
    "dqWorst": 0.1386,
    "dqAvg": 0.2168,
    "cqDelayAvg": 0.0904,
    "dSetup3SigmaAvg": 0.074,
    "dHoldSohmAvg": 0.0405,
    "area": 94.3291,
    "ckCap": 3.2254,
    "pLeakage": 3.5932,
    "pDyn": 4.1703,
    "pdpAvg": 0.6355
  },
  "60": {
    "eeckWorst": 0.2073,
    "eeckAvg": 0.1254,
    "cqDelayAvg": 0.0478,
    "eSetup3SigmaAvg": 0.037,
    "eHoldSohmAvg": 0.0152,
    "delayTranRfRatio": 1.2287,
    "area": 126.7065,
    "ckCap": 1.8554,
    "pLeakage": 1.0778,
    "pDyn": 5.9651,
    "pdpAvg": 0.6549
  },
  "61": {
    "dqWorst": 0.4406,
    "dqAvg": 0.1717,
    "cqDelayAvg": 0.0851,
    "dSetup3SigmaAvg": 0.0211,
    "dHoldSohmAvg": 0.0196,
    "area": 51.8476,
    "ckCap": 1.8228,
    "pLeakage": 0.1172,
    "pDyn": 6.5494,
    "pdpAvg": 0.2541
  },
  "62": {
    "eeckWorst": 0.5379,
    "eeckAvg": 0.216,
    "cqDelayAvg": 0.1804,
    "eSetup3SigmaAvg": 0.0277,
    "eHoldSohmAvg": 0.0788,
    "delayTranRfRatio": 1.1927,
    "area": 142.1808,
    "ckCap": 4.0722,
    "pLeakage": 2.2796,
    "pDyn": 5.4535,
    "pdpAvg": 0.1741
  },
  "63": {
    "dqWorst": 0.0706,
    "dqAvg": 0.2841,
    "cqDelayAvg": 0.1299,
    "dSetup3SigmaAvg": 0.1004,
    "dHoldSohmAvg": 0.0351,
    "area": 30.3715,
    "ckCap": 4.3878,
    "pLeakage": 0.3046,
    "pDyn": 2.0456,
    "pdpAvg": 0.5109
  },
  "64": {
    "eeckWorst": 0.2228,
    "eeckAvg": 0.3482,
    "cqDelayAvg": 0.0472,
    "eSetup3SigmaAvg": 0.117,
    "eHoldSohmAvg": 0.0565,
    "delayTranRfRatio": 1.4326,
    "area": 51.5962,
    "ckCap": 3.7787,
    "pLeakage": 2.1899,
    "pDyn": 5.4798,
    "pdpAvg": 0.7755
  },
  "65": {
    "dqWorst": 0.446,
    "dqAvg": 0.1125,
    "cqDelayAvg": 0.1628,
    "dSetup3SigmaAvg": 0.0771,
    "dHoldSohmAvg": 0.0605,
    "area": 152.6626,
    "ckCap": 1.9844,
    "pLeakage": 1.0524,
    "pDyn": 8.027,
    "pdpAvg": 0.1498
  },
  "66": {
    "eeckWorst": 0.1617,
    "eeckAvg": 0.0725,
    "cqDelayAvg": 0.0206,
    "eSetup3SigmaAvg": 0.0731,
    "eHoldSohmAvg": 0.0555,
    "delayTranRfRatio": 1.033,
    "area": 52.4067,
    "ckCap": 4.8296,
    "pLeakage": 3.3892,
    "pDyn": 5.6122,
    "pdpAvg": 0.6218
  },
  "67": {
    "dqWorst": 0.4196,
    "dqAvg": 0.2427,
    "cqDelayAvg": 0.1638,
    "dSetup3SigmaAvg": 0.0827,
    "dHoldSohmAvg": 0.075,
    "area": 79.5195,
    "ckCap": 3.904,
    "pLeakage": 3.1263,
    "pDyn": 10.9284,
    "pdpAvg": 0.7457
  },
  "68": {
    "eeckWorst": 0.1136,
    "eeckAvg": 0.0998,
    "cqDelayAvg": 0.0908,
    "eSetup3SigmaAvg": 0.1149,
    "eHoldSohmAvg": 0.0534,
    "delayTranRfRatio": 1.0309,
    "area": 37.4095,
    "ckCap": 4.7255,
    "pLeakage": 3.3737,
    "pDyn": 11.3293,
    "pdpAvg": 0.4554
  },
  "69": {
    "dqWorst": 0.2475,
    "dqAvg": 0.0517,
    "cqDelayAvg": 0.0292,
    "dSetup3SigmaAvg": 0.0575,
    "dHoldSohmAvg": 0.0292,
    "area": 55.0515,
    "ckCap": 1.3206,
    "pLeakage": 4.6191,
    "pDyn": 10.0807,
    "pdpAvg": 0.5219
  },
  "70": {
    "eeckWorst": 0.5269,
    "eeckAvg": 0.3499,
    "cqDelayAvg": 0.1746,
    "eSetup3SigmaAvg": 0.0477,
    "eHoldSohmAvg": 0.0084,
    "delayTranRfRatio": 1.405,
    "area": 85.8701,
    "ckCap": 4.5136,
    "pLeakage": 4.4013,
    "pDyn": 2.4234,
    "pdpAvg": 0.5309
  },
  "71": {
    "dqWorst": 0.3039,
    "dqAvg": 0.1628,
    "cqDelayAvg": 0.041,
    "dSetup3SigmaAvg": 0.0483,
    "dHoldSohmAvg": 0.03,
    "area": 113.8187,
    "ckCap": 5.6891,
    "pLeakage": 1.6166,
    "pDyn": 8.416,
    "pdpAvg": 0.2665
  },
  "72": {
    "eeckWorst": 0.5242,
    "eeckAvg": 0.2941,
    "cqDelayAvg": 0.1465,
    "eSetup3SigmaAvg": 0.0737,
    "eHoldSohmAvg": 0.0317,
    "delayTranRfRatio": 1.0586,
    "area": 155.8259,
    "ckCap": 3.1038,
    "pLeakage": 2.4943,
    "pDyn": 11.861,
    "pdpAvg": 0.5953
  },
  "73": {
    "dqWorst": 0.267,
    "dqAvg": 0.1416,
    "cqDelayAvg": 0.0631,
    "dSetup3SigmaAvg": 0.0498,
    "dHoldSohmAvg": 0.0617,
    "area": 107.5572,
    "ckCap": 5.1319,
    "pLeakage": 1.0169,
    "pDyn": 6.7259,
    "pdpAvg": 0.8356
  },
  "74": {
    "eeckWorst": 0.2859,
    "eeckAvg": 0.2595,
    "cqDelayAvg": 0.0479,
    "eSetup3SigmaAvg": 0.1462,
    "eHoldSohmAvg": 0.0568,
    "delayTranRfRatio": 0.9914,
    "area": 42.1729,
    "ckCap": 3.9398,
    "pLeakage": 2.6732,
    "pDyn": 1.3905,
    "pdpAvg": 0.8931
  },
  "75": {
    "dqWorst": 0.4152,
    "dqAvg": 0.1546,
    "cqDelayAvg": 0.047,
    "dSetup3SigmaAvg": 0.1015,
    "dHoldSohmAvg": 0.0424,
    "area": 120.3245,
    "ckCap": 3.7006,
    "pLeakage": 1.3488,
    "pDyn": 10.0663,
    "pdpAvg": 0.8824
  },
  "76": {
    "eeckWorst": 0.1946,
    "eeckAvg": 0.2154,
    "cqDelayAvg": 0.1082,
    "eSetup3SigmaAvg": 0.1391,
    "eHoldSohmAvg": 0.0482,
    "delayTranRfRatio": 1.5035,
    "area": 140.9638,
    "ckCap": 2.3746,
    "pLeakage": 3.8025,
    "pDyn": 5.1548,
    "pdpAvg": 0.8415
  },
  "77": {
    "dqWorst": 0.2531,
    "dqAvg": 0.2515,
    "cqDelayAvg": 0.0851,
    "dSetup3SigmaAvg": 0.0428,
    "dHoldSohmAvg": 0.049,
    "area": 159.8463,
    "ckCap": 3.5909,
    "pLeakage": 0.7558,
    "pDyn": 6.6014,
    "pdpAvg": 0.3172
  },
  "78": {
    "eeckWorst": 0.3394,
    "eeckAvg": 0.213,
    "cqDelayAvg": 0.1247,
    "eSetup3SigmaAvg": 0.055,
    "eHoldSohmAvg": 0.021,
    "delayTranRfRatio": 1.358,
    "area": 100.0517,
    "ckCap": 2.1313,
    "pLeakage": 3.7338,
    "pDyn": 0.8107,
    "pdpAvg": 0.6728
  },
  "79": {
    "dqWorst": 0.3321,
    "dqAvg": 0.2491,
    "cqDelayAvg": 0.1088,
    "dSetup3SigmaAvg": 0.083,
    "dHoldSohmAvg": 0.0666,
    "area": 157.3145,
    "ckCap": 3.6234,
    "pLeakage": 0.2258,
    "pDyn": 6.1768,
    "pdpAvg": 0.5353
  },
  "80": {
    "eeckWorst": 0.4888,
    "eeckAvg": 0.3123,
    "cqDelayAvg": 0.1213,
    "eSetup3SigmaAvg": 0.0836,
    "eHoldSohmAvg": 0.0438,
    "delayTranRfRatio": 1.378,
    "area": 77.397,
    "ckCap": 4.5323,
    "pLeakage": 0.7832,
    "pDyn": 5.793,
    "pdpAvg": 0.8726
  },
  "81": {
    "dqWorst": 0.1854,
    "dqAvg": 0.217,
    "cqDelayAvg": 0.1695,
    "dSetup3SigmaAvg": 0.1037,
    "dHoldSohmAvg": 0.0689,
    "area": 140.3079,
    "ckCap": 2.9661,
    "pLeakage": 1.5541,
    "pDyn": 8.709,
    "pdpAvg": 0.6859
  },
  "82": {
    "eeckWorst": 0.49,
    "eeckAvg": 0.0608,
    "cqDelayAvg": 0.0357,
    "eSetup3SigmaAvg": 0.0984,
    "eHoldSohmAvg": 0.0833,
    "delayTranRfRatio": 1.5979,
    "area": 124.5473,
    "ckCap": 3.2736,
    "pLeakage": 0.5176,
    "pDyn": 7.7148,
    "pdpAvg": 0.7866
  },
  "83": {
    "dqWorst": 0.2275,
    "dqAvg": 0.2174,
    "cqDelayAvg": 0.2278,
    "dSetup3SigmaAvg": 0.0151,
    "dHoldSohmAvg": 0.0647,
    "area": 61.0715,
    "ckCap": 2.9366,
    "pLeakage": 0.7415,
    "pDyn": 6.5146,
    "pdpAvg": 0.5137
  },
  "84": {
    "eeckWorst": 0.4525,
    "eeckAvg": 0.101,
    "cqDelayAvg": 0.0382,
    "eSetup3SigmaAvg": 0.1319,
    "eHoldSohmAvg": 0.0577,
    "delayTranRfRatio": 0.9927,
    "area": 147.7961,
    "ckCap": 1.6158,
    "pLeakage": 2.2405,
    "pDyn": 3.2715,
    "pdpAvg": 0.2372
  },
  "85": {
    "dqWorst": 0.0538,
    "dqAvg": 0.2473,
    "cqDelayAvg": 0.2273,
    "dSetup3SigmaAvg": 0.0845,
    "dHoldSohmAvg": 0.0168,
    "area": 81.8422,
    "ckCap": 2.7697,
    "pLeakage": 2.841,
    "pDyn": 7.7756,
    "pdpAvg": 0.3876
  },
  "86": {
    "eeckWorst": 0.1975,
    "eeckAvg": 0.3036,
    "cqDelayAvg": 0.0658,
    "eSetup3SigmaAvg": 0.0639,
    "eHoldSohmAvg": 0.0461,
    "delayTranRfRatio": 0.9898,
    "area": 100.0692,
    "ckCap": 4.0764,
    "pLeakage": 4.7653,
    "pDyn": 3.7542,
    "pdpAvg": 0.8804
  },
  "87": {
    "dqWorst": 0.3133,
    "dqAvg": 0.1041,
    "cqDelayAvg": 0.1502,
    "dSetup3SigmaAvg": 0.0854,
    "dHoldSohmAvg": 0.0609,
    "area": 26.8662,
    "ckCap": 4.2565,
    "pLeakage": 2.4095,
    "pDyn": 10.8786,
    "pdpAvg": 0.2647
  },
  "88": {
    "eeckWorst": 0.4555,
    "eeckAvg": 0.2321,
    "cqDelayAvg": 0.101,
    "eSetup3SigmaAvg": 0.0991,
    "eHoldSohmAvg": 0.0578,
    "delayTranRfRatio": 1.3422,
    "area": 120.93,
    "ckCap": 4.5573,
    "pLeakage": 4.0321,
    "pDyn": 7.6505,
    "pdpAvg": 0.814
  },
  "89": {
    "dqWorst": 0.3085,
    "dqAvg": 0.1134,
    "cqDelayAvg": 0.1214,
    "dSetup3SigmaAvg": 0.0738,
    "dHoldSohmAvg": 0.0599,
    "area": 32.6187,
    "ckCap": 2.4821,
    "pLeakage": 3.6005,
    "pDyn": 2.355,
    "pdpAvg": 0.1276
  },
  "90": {
    "eeckWorst": 0.3335,
    "eeckAvg": 0.3414,
    "cqDelayAvg": 0.1421,
    "eSetup3SigmaAvg": 0.1379,
    "eHoldSohmAvg": 0.0756,
    "delayTranRfRatio": 1.0056,
    "area": 135.4566,
    "ckCap": 3.5465,
    "pLeakage": 3.8808,
    "pDyn": 9.0347,
    "pdpAvg": 0.3115
  },
  "91": {
    "dqWorst": 0.0961,
    "dqAvg": 0.29,
    "cqDelayAvg": 0.0524,
    "dSetup3SigmaAvg": 0.1163,
    "dHoldSohmAvg": 0.0695,
    "area": 121.3903,
    "ckCap": 6.3857,
    "pLeakage": 4.6445,
    "pDyn": 9.7137,
    "pdpAvg": 0.3355
  },
  "92": {
    "eeckWorst": 0.4516,
    "eeckAvg": 0.0542,
    "cqDelayAvg": 0.1434,
    "eSetup3SigmaAvg": 0.0737,
    "eHoldSohmAvg": 0.0622,
    "delayTranRfRatio": 1.3379,
    "area": 101.8384,
    "ckCap": 5.4878,
    "pLeakage": 4.5164,
    "pDyn": 1.5676,
    "pdpAvg": 0.2181
  },
  "93": {
    "dqWorst": 0.06,
    "dqAvg": 0.2687,
    "cqDelayAvg": 0.1491,
    "dSetup3SigmaAvg": 0.1107,
    "dHoldSohmAvg": 0.0216,
    "area": 28.8504,
    "ckCap": 5.496,
    "pLeakage": 4.3696,
    "pDyn": 3.8356,
    "pdpAvg": 0.3734
  },
  "94": {
    "eeckWorst": 0.1457,
    "eeckAvg": 0.3339,
    "cqDelayAvg": 0.09,
    "eSetup3SigmaAvg": 0.079,
    "eHoldSohmAvg": 0.0133,
    "delayTranRfRatio": 1.5098,
    "area": 38.993,
    "ckCap": 3.3858,
    "pLeakage": 3.2348,
    "pDyn": 8.9947,
    "pdpAvg": 0.8519
  },
  "95": {
    "dqWorst": 0.2177,
    "dqAvg": 0.2304,
    "cqDelayAvg": 0.0555,
    "dSetup3SigmaAvg": 0.0556,
    "dHoldSohmAvg": 0.0124,
    "area": 88.5086,
    "ckCap": 3.1263,
    "pLeakage": 4.5697,
    "pDyn": 0.6828,
    "pdpAvg": 0.3398
  },
  "96": {
    "eeckWorst": 0.2884,
    "eeckAvg": 0.3352,
    "cqDelayAvg": 0.2168,
    "eSetup3SigmaAvg": 0.0239,
    "eHoldSohmAvg": 0.0633,
    "delayTranRfRatio": 1.2356,
    "area": 156.898,
    "ckCap": 2.8444,
    "pLeakage": 1.9412,
    "pDyn": 2.5208,
    "pdpAvg": 0.1187
  },
  "97": {
    "dqWorst": 0.3892,
    "dqAvg": 0.1528,
    "cqDelayAvg": 0.1724,
    "dSetup3SigmaAvg": 0.0806,
    "dHoldSohmAvg": 0.0498,
    "area": 22.99,
    "ckCap": 5.2847,
    "pLeakage": 1.207,
    "pDyn": 1.7733,
    "pdpAvg": 0.5125
  },
  "98": {
    "eeckWorst": 0.1122,
    "eeckAvg": 0.2795,
    "cqDelayAvg": 0.0676,
    "eSetup3SigmaAvg": 0.0402,
    "eHoldSohmAvg": 0.0789,
    "delayTranRfRatio": 1.0628,
    "area": 40.6576,
    "ckCap": 5.933,
    "pLeakage": 0.0635,
    "pDyn": 10.3434,
    "pdpAvg": 0.1388
  },
  "99": {
    "dqWorst": 0.102,
    "dqAvg": 0.0977,
    "cqDelayAvg": 0.0601,
    "dSetup3SigmaAvg": 0.0827,
    "dHoldSohmAvg": 0.0069,
    "area": 22.0804,
    "ckCap": 5.3029,
    "pLeakage": 1.1802,
    "pDyn": 4.0881,
    "pdpAvg": 0.1651
  },
  "100": {
    "eeckWorst": 0.1046,
    "eeckAvg": 0.2725,
    "cqDelayAvg": 0.141,
    "eSetup3SigmaAvg": 0.1144,
    "eHoldSohmAvg": 0.0455,
    "delayTranRfRatio": 1.4224,
    "area": 91.8533,
    "ckCap": 1.4216,
    "pLeakage": 2.4432,
    "pDyn": 11.3614,
    "pdpAvg": 0.0486
  }
}